skyr.py
skyr-0.3.1.dist-info/METADATA
skyr-0.3.1.dist-info/WHEEL
skyr-0.3.1.dist-info/entry_points.txt
skyr-0.3.1.dist-info/licenses/LICENSE
skyr-0.3.1.dist-info/RECORD
