Metadata-Version: 2.1
Name: skyr
Version: 0.3.1
Summary: A low-fat task runner.
Project-URL: Issues, https://github.com/kytta/skyr/issues
Project-URL: Source, https://github.com/kytta/skyr
Author-email: Nikita Karamov <me@kytta.dev>
Maintainer-email: Nikita Karamov <me@kytta.dev>
License-Expression: ISC
License-File: LICENSE
Classifier: Development Status :: 3 - Alpha
Classifier: Environment :: Console
Classifier: Intended Audience :: Developers
Classifier: Intended Audience :: System Administrators
Classifier: License :: OSI Approved :: ISC License (ISCL)
Classifier: Operating System :: MacOS
Classifier: Operating System :: POSIX
Classifier: Operating System :: Unix
Classifier: Programming Language :: Python
Classifier: Programming Language :: Python :: 3 :: Only
Classifier: Programming Language :: Python :: 3.9
Classifier: Programming Language :: Python :: 3.10
Classifier: Programming Language :: Python :: 3.11
Classifier: Programming Language :: Python :: 3.12
Classifier: Topic :: Software Development :: Build Tools
Classifier: Topic :: Utilities
Classifier: Typing :: Typed
Requires-Python: >=3.9
